ctfbe/__init__.py
ctfbe-1.0.2.dist-info/LICENSE
ctfbe-1.0.2.dist-info/METADATA
ctfbe-1.0.2.dist-info/WHEEL
ctfbe-1.0.2.dist-info/top_level.txt
ctfbe-1.0.2.dist-info/RECORD
