Metadata-Version: 2.1
Name: ctfbe
Version: 1.0.2
Summary: A simple project to encrypt data and files. This program encrypts any type of file, whatever its size. Nothing can be decrypted without the password.
Home-page: https://github.com/yasserbdj96/ctfbe
Author: Yasser Bdj (Boudjada Yasser)
Author-email: yasser.bdj96@gmail.com
License: MIT License
Project-URL: Author WebSite, https://yasserbdj96.github.io/
Keywords: yasserbdj96,python,CTFBE,(codes,texts,files,big,data,encrypted),A,simple,project,to,encrypt,data,and,files.,This,program,encrypts,any,type,of,file,,whatever,its,size.,Nothing,can,be,decrypted,without,the,password.
Platform: UNKNOWN
Classifier: Development Status :: 5 - Production/Stable
Classifier: Intended Audience :: Developers
Classifier: License :: OSI Approved :: MIT License
Classifier: Programming Language :: Python :: 3
Classifier: Operating System :: Unix
Classifier: Operating System :: MacOS :: MacOS X
Classifier: Operating System :: Microsoft :: Windows
Classifier: Topic :: Software Development :: Build Tools
Classifier: Topic :: Software Development :: Libraries :: Python Modules
Classifier: Topic :: Communications :: Email
Requires-Python: >=3.x.x
Requires-Dist: pipincluder
